prs_lib/__init__.py
prs_lib/block.py
prs_lib/config.py
prs_lib/contract.py
prs_lib/dapp.py
prs_lib/draft.py
prs_lib/file.py
prs_lib/finance.py
prs_lib/keystore.py
prs_lib/order.py
prs_lib/request.py
prs_lib/sign_utility.py
prs_lib/subscription.py
prs_lib/task.py
prs_lib/user.py
prs_lib/util.py
prs_lib/validator.py
prs_lib-0.0.4.dist-info/LICENSE
prs_lib-0.0.4.dist-info/METADATA
prs_lib-0.0.4.dist-info/WHEEL
prs_lib-0.0.4.dist-info/top_level.txt
prs_lib-0.0.4.dist-info/RECORD
