Metadata-Version: 2.1
Name: prs-lib
Version: 0.0.4
Summary: prs lib
Home-page: https://github.com/Press-One/prs-lib-py
Author: PRESS.one
Author-email: dev@press.one
License: MIT
Platform: any
Classifier: Development Status :: 5 - Production/Stable
Classifier: Intended Audience :: Developers
Classifier: License :: OSI Approved :: MIT License
Classifier: Operating System :: OS Independent
Classifier: Programming Language :: Python
Classifier: Programming Language :: Python :: 3.6
Classifier: Programming Language :: Python :: 3.7
Classifier: Topic :: Software Development :: Libraries :: Python Modules
Requires-Python: >=3.6
Requires-Dist: requests
Requires-Dist: prs-utility
Provides-Extra: dev
Requires-Dist: pytest (>=3) ; extra == 'dev'
Requires-Dist: coverage ; extra == 'dev'
Requires-Dist: tox ; extra == 'dev'
Requires-Dist: twine ; extra == 'dev'
